{"cached_at": "2025-04-01T18:52:29.397306", "value": {"cast": [{"adult": false, "gender": 1, "id": 64774, "known_for_department": "Acting", "name": "Natalia Oreiro", "original_name": "Natalia Oreiro", "popularity": 0.5991, "profile_path": "/mPXbbWPifRNHoi9HFCUQI8FDKG.jpg", "character": "Esperanza Mu\u00f1oz / La Monita", "credit_id": "56e1f125c3a36870010002f5", "order": 0}, {"adult": false, "gender": 2, "id": 1245110, "known_for_department": "Acting", "name": "Facundo Arana", "original_name": "Facundo Arana", "popularity": 0.18, "profile_path": "/jwYwik29HrMHoIDrkpMBKZacYxx.jpg", "character": "Mart\u00edn Quesada", "credit_id": "56e1f13dc3a3686ffd0002ea", "order": 1}, {"adult": false, "gender": 2, "id": 130753, "known_for_department": "Acting", "name": "Carlos Belloso", "original_name": "Carlos Belloso", "popularity": 0.1084, "profile_path": "/zP0dVhtnTJHEUj814WyELtlvWbz.jpg", "character": "Enrique 'Quique' Ferreti", "credit_id": "56e1f162c3a3686ff5000336", "order": 2}, {"adult": false, "gender": 1, "id": 562364, "known_for_department": "Acting", "name": "Carla Peterson", "original_name": "Carla Peterson", "popularity": 0.4715, "profile_path": "/wzu3UNvxIlk1i9uWjcFi8ANrAyl.jpg", "character": "Constanza Ins\u00faa", "credit_id": "56e1f17cc3a3686ff9000349", "order": 3}, {"adult": false, "gender": 2, "id": 150069, "known_for_department": "Acting", "name": "Marcelo Mazzarello", "original_name": "Marcelo Mazzarello", "popularity": 0.1076, "profile_path": "/nHtL5gVDCCrT2A67g6GPVSlqnPh.jpg", "character": "Miguel Quesada", "credit_id": "56e1f1ca9251417894000335", "order": 4}, {"adult": false, "gender": 0, "id": 1588661, "known_for_department": "Acting", "name": "Nicol\u00e1s D'Agostino", "original_name": "Nicol\u00e1s D'Agostino", "popularity": 0.0712, "profile_path": null, "character": "Tony", "credit_id": "56e1f1e6c3a3686ff2000356", "order": 5}, {"adult": false, "gender": 2, "id": 993419, "known_for_department": "Acting", "name": "Gino Renni", "original_name": "Gino Renni", "popularity": 0.2425, "profile_path": "/uyLCAARN6VdPQC5XWoJHylgFpVB.jpg", "character": "Hector Hugo", "credit_id": "56e1f20c92514178910002dd", "order": 6}, {"adult": false, "gender": 1, "id": 1020042, "known_for_department": "Acting", "name": "Griselda Siciliani", "original_name": "Griselda Siciliani", "popularity": 0.2369, "profile_path": "/sJTDde4BWJHR9IIUn21EG36hnSP.jpg", "character": "Deborah 'Debi' Quesada", "credit_id": "5f9c8d05ca8354003a4b2c79", "order": 7}, {"adult": false, "gender": 1, "id": 1035542, "known_for_department": "Acting", "name": "Jimena Bar\u00f3n", "original_name": "Jimena Bar\u00f3n", "popularity": 0.1092, "profile_path": "/oJ1QXnxM2YlHktI5x4Yuh2nrPHt.jpg", "character": "Mar\u00eda Victoria L\u00f3pez", "credit_id": "60cb5e9b05a533002a24d0d8", "order": 8}, {"adult": false, "gender": 2, "id": 3453749, "known_for_department": "Acting", "name": "Gustavo Berm\u00fadez", "original_name": "Gustavo Berm\u00fadez", "popularity": 0.1048, "profile_path": "/heCHCIYzIFY04dkwFNehkQApJ6n.jpg", "character": "V\u00edctor Lobo", "credit_id": "62bb3c7e8b959e0093ef448c", "order": 9}], "crew": [{"adult": false, "gender": 2, "id": 1073027, "known_for_department": "Directing", "name": "Daniel De Felippo", "original_name": "Daniel De Felippo", "popularity": 0.0718, "profile_path": null, "credit_id": "5bc349e492514179c4043343", "department": "Directing", "job": "Director"}, {"adult": false, "gender": 2, "id": 2033135, "known_for_department": "Production", "name": "Diego Carabelli", "original_name": "Diego Carabelli", "popularity": 0.0496, "profile_path": null, "credit_id": "5bc34a42c3a3682d60049e92", "department": "Production", "job": "Executive Producer"}, {"adult": false, "gender": 2, "id": 81012, "known_for_department": "Creator", "name": "Adri\u00e1n Suar", "original_name": "Adri\u00e1n Suar", "popularity": 0.3892, "profile_path": "/a75QAiWiI4jJoGyYY2Tw6ELAkkA.jpg", "credit_id": "5bc34a5692514179c40433b3", "department": "Production", "job": "Producer"}, {"adult": false, "gender": 0, "id": 1621259, "known_for_department": "Acting", "name": "Camilo Jos\u00e9 Torres", "original_name": "Camilo Jos\u00e9 Torres", "popularity": 0.0214, "profile_path": null, "credit_id": "5bc34a6a92514179c40433bb", "department": "Writing", "job": "Writer"}], "id": 14471}}