{"cached_at": "2025-04-01T18:50:00.047754", "value": {"cast": [{"adult": false, "gender": 1, "id": 1287711, "known_for_department": "Acting", "name": "Fuka Koshiba", "original_name": "\u5c0f\u829d\u98a8\u82b1", "popularity": 0.4624, "profile_path": "/p3ZaF4chfjSwKVBEP12fcpi17b3.jpg", "character": "Mita Sakura", "credit_id": "667a7d77a50baf51001594aa", "order": 0}, {"adult": false, "gender": 1, "id": 1029718, "known_for_department": "Acting", "name": "Yuko Oshima", "original_name": "\u5927\u5cf6\u512a\u5b50", "popularity": 3.3511, "profile_path": "/70brQ4Zjaz4oW1pYIP8ZHuM6D7J.jpg", "character": "Tsukimoto Makoto", "credit_id": "667a7d834be38f218a8be344", "order": 1}, {"adult": false, "gender": 2, "id": 2293427, "known_for_department": "Acting", "name": "Ryohei Abe", "original_name": "\u963f\u90e8\u4eae\u5e73", "popularity": 0.1813, "profile_path": "/1yK8jYCTaOgzXk7cewPF2dTly4t.jpg", "character": "Teshima Junnosuke", "credit_id": "667a7dd60c7527d620f9bd27", "order": 2}, {"adult": false, "gender": 2, "id": 552575, "known_for_department": "Acting", "name": "Kotaro Yoshida", "original_name": "\u5409\u7530\u92fc\u592a\u90ce", "popularity": 0.6992, "profile_path": "/uu27aDu5iCBHiJ3GFtOGWm9FBTP.jpg", "character": "Tonegawa Joji", "credit_id": "667a7e007e57ec07ee567d5c", "order": 3}, {"adult": false, "gender": 2, "id": 1251804, "known_for_department": "Acting", "name": "Shigeyuki Totsugi", "original_name": "\u6238\u6b21\u91cd\u5e78", "popularity": 0.5183, "profile_path": "/pK3B7H4qrzLy7nKr0lFKfqNRq91.jpg", "character": "Horiguchi Naofumi", "credit_id": "667a7e0d42048986004cb8cc", "order": 4}, {"adult": false, "gender": 2, "id": 1257291, "known_for_department": "Acting", "name": "Kazuaki Hankai", "original_name": "\u534a\u6d77\u4e00\u6643", "popularity": 0.1483, "profile_path": "/lRSlFUdgWh6lXkzfaOUbRxmRycI.jpg", "character": "Muto Haruo", "credit_id": "667a7e18d2246ffbd1a0af65", "order": 5}, {"adult": false, "gender": 1, "id": 1573480, "known_for_department": "Acting", "name": "Miki Yanagi", "original_name": "\u67f3\u7f8e\u7a00", "popularity": 0.3173, "profile_path": "/u6UxuVzXxTlfd12VId2eHCschs3.jpg", "character": "Serizawa Natsu", "credit_id": "667a7e223fff4ceb6ff9bd4c", "order": 6}, {"adult": false, "gender": 1, "id": 974738, "known_for_department": "Acting", "name": "Reiko Takashima", "original_name": "\u9ad8\u5cf6\u793c\u5b50", "popularity": 1.2387, "profile_path": "/p6FfG2bCKHK8bVliQP335SOlRiz.jpg", "character": "Hayase Ikumi", "credit_id": "667a7e2d4af935a80cf699f7", "order": 7}, {"adult": false, "gender": 1, "id": 3057742, "known_for_department": "Acting", "name": "Riko Kawase", "original_name": "\u5ddd\u702c\u8389\u5b50", "popularity": 0.1404, "profile_path": "/nsbch3280InJ1RQ3Zgwy4ui3Qb6.jpg", "character": "\u897f\u672c\u6c99\u8036\u9999", "credit_id": "66c3605619fcb9bc2696e7bb", "order": 8}], "crew": [{"adult": false, "gender": 2, "id": 1276841, "known_for_department": "Writing", "name": "Hiroyuki Yatsu", "original_name": "\u516b\u6d25\u5f18\u5e78", "popularity": 0.1566, "profile_path": "/ky6ZJ3nTE7XlgMvnuGCNwob6RDc.jpg", "credit_id": "667a7ced0c7527d620f9bd05", "department": "Writing", "job": "Writer"}, {"adult": false, "gender": 2, "id": 1992994, "known_for_department": "Directing", "name": "Shintaro Sugawara", "original_name": "\u83c5\u539f\u4f38\u592a\u90ce", "popularity": 0.1082, "profile_path": null, "credit_id": "667a7cf928fec8c5868be1c1", "department": "Directing", "job": "Director"}, {"adult": false, "gender": 2, "id": 127885, "known_for_department": "Directing", "name": "Tar\u014d \u014ctani", "original_name": "\u5927\u8c37\u592a\u90ce", "popularity": 0.0912, "profile_path": null, "credit_id": "667a7d0860249e210ef9bd0d", "department": "Directing", "job": "Director"}, {"adult": false, "gender": 0, "id": 2372789, "known_for_department": "Directing", "name": "Shigekatsu Honda", "original_name": "\u672c\u591a\u7e41\u52dd", "popularity": 0.042, "profile_path": null, "credit_id": "667a7d3fe84f943d28e45579", "department": "Production", "job": "Producer"}, {"adult": false, "gender": 2, "id": 1493765, "known_for_department": "Sound", "name": "Masaru Yokoyama", "original_name": "\u6a2a\u5c71\u514b", "popularity": 0.1065, "profile_path": "/isDF4Cm7oqNDw9UgOI7DvFFJf7y.jpg", "credit_id": "667a7d29a50baf51001594a0", "department": "Crew", "job": "Compositor"}, {"adult": false, "gender": 0, "id": 1732482, "known_for_department": "Writing", "name": "Tomoharu Sato", "original_name": "\u4f50\u85e4\u53cb\u6cbb", "popularity": 0.0362, "profile_path": null, "credit_id": "66c3654b4d2976cb237e884e", "department": "Writing", "job": "Writer"}], "id": 256300}}