{"cached_at": "2025-03-31T22:06:45.531184", "value": {"cast": [{"adult": false, "gender": 0, "id": 2363930, "known_for_department": "Acting", "name": "Jason Cavanagh", "original_name": "Jason Cavanagh", "popularity": 0.0214, "profile_path": null, "character": "Daryl", "credit_id": "673c027815333e736195d4b2", "order": 0}, {"adult": false, "gender": 0, "id": 3040351, "known_for_department": "Acting", "name": "Tim Clarke", "original_name": "Tim Clarke", "popularity": 0.0765, "profile_path": null, "character": "Anthony", "credit_id": "673c02b34d6db00d93d4bc2e", "order": 1}, {"adult": false, "gender": 0, "id": 5068009, "known_for_department": "Acting", "name": "Frieda Commitment", "original_name": "Frieda Commitment", "popularity": 0.0071, "profile_path": null, "character": "", "credit_id": "673c02be19ac32ceb1bd1415", "order": 2}, {"adult": false, "gender": 0, "id": 2363929, "known_for_department": "Acting", "name": "Tom Farrah", "original_name": "Tom Farrah", "popularity": 0.0336, "profile_path": null, "character": "Stuart", "credit_id": "673c02d919ac32ceb1bd1433", "order": 3}, {"adult": false, "gender": 0, "id": 5068011, "known_for_department": "Acting", "name": "Wesley Forke", "original_name": "Wesley Forke", "popularity": 0.0214, "profile_path": null, "character": "Peter", "credit_id": "673c02f68fbc08961a2392e0", "order": 4}, {"adult": false, "gender": 0, "id": 4240234, "known_for_department": "Acting", "name": "Adam Mountain", "original_name": "Adam Mountain", "popularity": 0.0143, "profile_path": null, "character": "Ryan", "credit_id": "673c02ff19ac32ceb1bd1460", "order": 5}, {"adult": false, "gender": 0, "id": 5068013, "known_for_department": "Acting", "name": "Freya Pragt", "original_name": "Freya Pragt", "popularity": 0.0, "profile_path": null, "character": "Louise", "credit_id": "673c03254d6db00d93d4bc6d", "order": 6}], "crew": [], "id": 277485}}