{"cached_at": "2025-04-01T18:53:54.709107", "value": {"id": 120454, "name": "Spotlight", "original_name": "Spotlight", "overview": "Profiles and interviews with sports personalities.", "first_air_date": "2016-09-26", "genre_ids": [], "popularity": 22.7315, "vote_average": 5.5, "vote_count": 1, "genres": [{"id": 99, "name": "Documentary"}, {"id": 10767, "name": "Talk"}], "networks": [{"id": 775, "name": "Nickelodeon"}], "status": "Returning Series", "type": "Scripted", "number_of_seasons": 6, "number_of_episodes": 296, "in_production": true, "languages": ["de"], "last_air_date": "2023-04-19"}}