{"cached_at": "2025-03-31T22:11:17.231458", "value": {"id": 109994, "name": "The Romance of the White Hair Maiden", "original_name": "\u767d\u9aee\u9b54\u5973\u50b3", "overview": "", "first_air_date": "1995-01-09", "genre_ids": [], "popularity": 2.094, "vote_average": 0.0, "vote_count": 0, "genres": [{"id": 18, "name": "Drama"}], "networks": [{"id": 48, "name": "TVB Jade"}], "status": "Ended", "type": "Scripted", "number_of_seasons": 1, "number_of_episodes": 20, "in_production": false, "languages": ["cn"], "last_air_date": "1995-02-03"}}