{"cached_at": "2025-03-30T18:02:15.640781", "value": {"id": 155716, "name": "Looking at Love and Death", "original_name": "\u611b\u3068\u6b7b\u3092\u307f\u3064\u3081\u3066", "overview": "", "first_air_date": "2006-03-18", "genre_ids": [], "popularity": 0.3873, "vote_average": 0.0, "vote_count": 0, "genres": [{"id": 18, "name": "Drama"}, {"id": 10751, "name": "Family"}], "networks": [{"id": 103, "name": "tv asahi"}], "status": "Ended", "type": "Scripted", "number_of_seasons": 1, "number_of_episodes": 2, "in_production": false, "languages": [], "last_air_date": "2006-03-19"}}