{"cached_at": "2025-04-01T18:45:49.547658", "value": {"id": 78052, "name": "Marry Me Now", "original_name": "\uac19\uc774 \uc0b4\ub798\uc694", "overview": "Park Yoo-Ha studied hard in medical school and finished her intern course. She works hard to become a doctor due to her father. Her father raised 4 children by himself and her oldest sister also sacrificed for the family. Park Yoo-Ha is not interested in other people. Suddenly, her father marries a woman rich enough to own a building.\n\nMeanwhile, Jung Eun-Tae works as a doctor. He volunteered for performing medical service abroad, but he comes back to Korea. Jung Eun-Tae is not interested in marriage, because his father placed priority on his medical work over family and Jung Eun-Tae believes he is like his father.", "first_air_date": "2018-03-17", "genre_ids": [], "popularity": 10.4974, "vote_average": 5.6, "vote_count": 5, "genres": [{"id": 18, "name": "Drama"}, {"id": 10751, "name": "Family"}], "networks": [{"id": 342, "name": "KBS2"}], "status": "Ended", "type": "Scripted", "number_of_seasons": 1, "number_of_episodes": 50, "in_production": false, "languages": ["ko"], "last_air_date": "2018-09-09"}}