{"cached_at": "2025-03-31T22:01:45.104380", "value": {"id": 101934, "name": "Crash! Insignificant Roommates", "original_name": "\uc6b0\ub2f9\ud0d5\ud0d5 \ud558\ucc2e\uc740 \uba54\uc774\ud2b8", "overview": "It tells the story and episodes of the 10 close boys who have lived together since high school. A group of young boys who find the destination and explore the universe in the early days of university. They were expecting to meet paradise when they entered university. This is a great chance for those who are sad and want to be alone. However, when they started to experience it, they realised that that was not true. They portray the love, friendship, and dreams of the 20s.\n\nA group of boys who face problems in their lives and want to enjoy their life by making friends and girlfriends, but they are wrong.", "first_air_date": "2019-10-16", "genre_ids": [], "popularity": 0.0281, "vote_average": 3.0, "vote_count": 1, "genres": [{"id": 18, "name": "Drama"}, {"id": 35, "name": "Comedy"}], "networks": [], "status": "Ended", "type": "Scripted", "number_of_seasons": 1, "number_of_episodes": 8, "in_production": false, "languages": ["ko"], "last_air_date": "2019-11-09"}}