{"cached_at": "2025-04-01T18:56:28.938446", "value": {"cast": [{"adult": false, "gender": 1, "id": 1838200, "known_for_department": "Acting", "name": "Zhu Xudan", "original_name": "\u795d\u7dd2\u4e39", "popularity": 0.8235, "profile_path": "/bfqvBRuDi56O2WB1Hvg6IPeITlm.jpg", "character": "Cao Xuanxuan / Zhou Na", "credit_id": "6746ca98301fb4f6b61799b9", "order": 0}, {"adult": false, "gender": 2, "id": 3133673, "known_for_department": "Acting", "name": "Zhai Xiaowen", "original_name": "\u7fdf\u6f47\u95fb", "popularity": 1.6894, "profile_path": "/sX4Fhh35IZxJwultxPSilG8C8Ng.jpg", "character": "Guo Zijie", "credit_id": "6746caa3c46ebd1fd4a41925", "order": 1}, {"adult": false, "gender": 2, "id": 3050501, "known_for_department": "Acting", "name": "Guo Cheng", "original_name": "Guo Cheng", "popularity": 0.2376, "profile_path": "/2M5aAGo0g3fGTtP3JGldIOp2PzQ.jpg", "character": "Sun Weiyan", "credit_id": "677c9a7355d4b38f9367432c", "order": 2}, {"adult": false, "gender": 1, "id": 3106473, "known_for_department": "Acting", "name": "Xu Muchan", "original_name": "\u5f90\u6c90\u5a75", "popularity": 0.1359, "profile_path": "/o66k7pPYBSwCL8ipdRRwxE7vqdY.jpg", "character": "He Chun", "credit_id": "677c9a7c15cafe8aad74a464", "order": 3}, {"adult": false, "gender": 1, "id": 3091322, "known_for_department": "Acting", "name": "Li Zixuan", "original_name": "\u674e\u5b50\u7487", "popularity": 0.1464, "profile_path": "/2P9n2dwqRXFx5InDfxdNLsN6NAn.jpg", "character": "Zhao Xiaolin", "credit_id": "67806f531431e0591abb1662", "order": 4}, {"adult": false, "gender": 1, "id": 2850871, "known_for_department": "Acting", "name": "Song Xinran", "original_name": "Song Xinran", "popularity": 0.0738, "profile_path": "/wT3w76cuIRBmQSSqTsuTObYfCnI.jpg", "character": "Ruo Hui", "credit_id": "67806f6bee84fa4def7aff32", "order": 5}, {"adult": false, "gender": 1, "id": 2709803, "known_for_department": "Acting", "name": "Yu Xintong", "original_name": "Yu Xintong", "popularity": 0.131, "profile_path": "/48PQqsxJBzYUahtewN3AHaqaeS.jpg", "character": "Ouyang Mingyue", "credit_id": "67806f98ed679e53f87b1804", "order": 6}, {"adult": false, "gender": 2, "id": 1784502, "known_for_department": "Acting", "name": "Ying Haoming", "original_name": "Ying Haoming", "popularity": 0.1943, "profile_path": "/fbyZuhlhy1kKOJPMCU80oxoB7dQ.jpg", "character": "Guo Zilu", "credit_id": "6746cab9398aa0b26d8907bb", "order": 7}], "crew": [{"adult": false, "gender": 2, "id": 3800358, "known_for_department": "Directing", "name": "Zhu Shaojie", "original_name": "\u6731\u5c11\u6770", "popularity": 0.1769, "profile_path": "/fZaDDhsuAMf1tYcLEX2mXjkX2It.jpg", "credit_id": "67806ff912667968854ebb5b", "department": "Directing", "job": "Director"}, {"adult": false, "gender": 1, "id": 4700611, "known_for_department": "Writing", "name": "\u5f20\u5b50\u7487", "original_name": "\u5f20\u5b50\u7487", "popularity": 0.0, "profile_path": null, "credit_id": "6780709112667968854ebb8a", "department": "Writing", "job": "Writer"}, {"adult": false, "gender": 2, "id": 5169823, "known_for_department": "Writing", "name": "\u53f6\u6811", "original_name": "\u53f6\u6811", "popularity": 0.0, "profile_path": null, "credit_id": "678070c91431e0591abb16af", "department": "Writing", "job": "Writer"}], "id": 278247}}