{"cached_at": "2025-03-31T22:05:43.765790", "value": {"id": 284160, "name": "Breath", "original_name": "\u0646\u0641\u0633", "overview": "A ballerina losing her sight finds hope in a young Syrian refugee who helps her rebuild her confidence. But as love blooms between them, her dad's powerful interference shatters her world, pulling her back to square one.", "first_air_date": "2025-03-01", "genre_ids": [], "popularity": 0.3085, "vote_average": 0.0, "vote_count": 0, "genres": [{"id": 18, "name": "Drama"}], "networks": [], "status": "Returning Series", "type": "Scripted", "number_of_seasons": 1, "number_of_episodes": 21, "in_production": true, "languages": ["ar"], "last_air_date": "2025-03-21"}}