{"cached_at": "2025-03-31T21:59:47.414852", "value": {"id": 115745, "name": "Club Friday The Series Season 8: True Love\u2026or Bond", "original_name": "Club Friday The Series 8 \u0e23\u0e31\u0e01\u0e41\u0e17\u0e49...\u0e21\u0e35\u0e2b\u0e23\u0e37\u0e2d\u0e44\u0e21\u0e48\u0e21\u0e35\u0e08\u0e23\u0e34\u0e07 \u0e15\u0e2d\u0e19 \u0e23\u0e31\u0e01\u0e41\u0e17\u0e49\u0e2b\u0e23\u0e37\u0e2d\u0e41\u0e04\u0e48...\u0e1c\u0e39\u0e01\u0e1e\u0e31\u0e19", "overview": "", "first_air_date": "2016-11-26", "genre_ids": [], "popularity": 0.2048, "vote_average": 0.0, "vote_count": 0, "genres": [{"id": 18, "name": "Drama"}], "networks": [{"id": 1974, "name": "GMM 25"}], "status": "Ended", "type": "Scripted", "number_of_seasons": 1, "number_of_episodes": 5, "in_production": false, "languages": ["th"], "last_air_date": "2016-12-24"}}