{"cached_at": "2025-03-31T22:01:15.460837", "value": {"id": 39198, "name": "Heartstrings", "original_name": "\ub10c \ub0b4\uac8c \ubc18\ud588\uc5b4", "overview": "Lee Gyu Won is the daughter of one of the top three maestros of pansori and is also a gayageum prot\u00e9g\u00e9 herself. Following her grandfather\u2019s wishes for her to study the gayageum, she enrolls as a major of gugak, or traditional Korean music. Lee Shin is unfriendly, yet a clever student in the Applied Music Department who also is the famed vocalist and talented guitarist of the handsome band named The Stupid. With charming looks equal to those of a handsome character in a romance comic and a cold, taciturn personality, he thinks gugak is boring and belittles it. As the vocalist Lee Shin and Gayageum Prot\u00e9g\u00e9 Lee Gyu Won passionately confront each other to champion their respective music, they soon fall in love.", "first_air_date": "2011-06-29", "genre_ids": [], "popularity": 2.3226, "vote_average": 7.038, "vote_count": 39, "genres": [{"id": 35, "name": "Comedy"}, {"id": 18, "name": "Drama"}], "networks": [{"id": 97, "name": "MBC"}], "status": "Ended", "type": "Scripted", "number_of_seasons": 1, "number_of_episodes": 15, "in_production": false, "languages": ["ko", "en"], "last_air_date": "2011-08-18"}}