{"cached_at": "2025-03-31T22:04:40.897436", "value": {"cast": [{"adult": false, "gender": 1, "id": 177231, "known_for_department": "Acting", "name": "Lana Parrilla", "original_name": "Lana Parrilla", "popularity": 1.1677, "profile_path": "/jw0H1hMEW9xJ4atAzGMMRUFiys.jpg", "character": "Eva Zambrano", "credit_id": "52585797760ee346610c3969", "order": 0}, {"adult": false, "gender": 2, "id": 18325, "known_for_department": "Acting", "name": "Jeremy Northam", "original_name": "Jeremy Northam", "popularity": 0.6144, "profile_path": "/h5u9lNQSPpYBMTYemSD2wC89X4q.jpg", "character": "Matthew Proctor", "credit_id": "52585797760ee346610c3959", "order": 1}, {"adult": false, "gender": 2, "id": 6858, "known_for_department": "Acting", "name": "Mike Vogel", "original_name": "Mike Vogel", "popularity": 1.0792, "profile_path": "/5pOkcl3D9JnGMR50gSDaAY2TIry.jpg", "character": "Chris Deleo", "credit_id": "52585797760ee346610c3989", "order": 2}, {"adult": false, "gender": 1, "id": 78197, "known_for_department": "Acting", "name": "Elisabeth Harnois", "original_name": "Elisabeth Harnois", "popularity": 0.6302, "profile_path": "/yq9H8T5urAGhzvEBxbw4gBjvDN2.jpg", "character": "Serena Warren", "credit_id": "52585797760ee346610c3979", "order": 3}, {"adult": false, "gender": 2, "id": 88183, "known_for_department": "Acting", "name": "Omar Gooding", "original_name": "Omar Gooding", "popularity": 0.5111, "profile_path": "/qDZ8WVbMQ3inSUn4k7XWqgCAIvm.jpg", "character": "Tuck Brody", "credit_id": "52585797760ee346610c3949", "order": 4}], "crew": [{"adult": false, "gender": 2, "id": 1237491, "known_for_department": "Writing", "name": "Jeffrey Lieber", "original_name": "Jeffrey Lieber", "popularity": 0.1915, "profile_path": null, "credit_id": "5d4874912d1e400199c028a7", "department": "Production", "job": "Executive Producer"}, {"adult": false, "gender": 2, "id": 770, "known_for_department": "Production", "name": "Jerry Bruckheimer", "original_name": "Jerry Bruckheimer", "popularity": 0.9066, "profile_path": "/sYjNrmbMi4DGAPX6Kt8wVy7LNXI.jpg", "credit_id": "5d487484a0be283483a35b5d", "department": "Production", "job": "Executive Producer"}, {"adult": false, "gender": 2, "id": 1224406, "known_for_department": "Production", "name": "Jonathan Littman", "original_name": "Jonathan Littman", "popularity": 0.1607, "profile_path": null, "credit_id": "5d48749e2d1e405082c0da72", "department": "Production", "job": "Executive Producer"}, {"adult": false, "gender": 2, "id": 1225826, "known_for_department": "Writing", "name": "Steven Maeda", "original_name": "Steven Maeda", "popularity": 0.0671, "profile_path": null, "credit_id": "5d4874a9c1e56e0017689208", "department": "Production", "job": "Executive Producer"}, {"adult": false, "gender": 2, "id": 92336, "known_for_department": "Costume & Make-Up", "name": "Clinton Wayne", "original_name": "Clinton Wayne", "popularity": 0.2103, "profile_path": "/eYKuhXBXpZ16Yu8hMhEkOTSAbPN.jpg", "credit_id": "67401fd65cac041cfae27110", "department": "Costume & Make-Up", "job": "Special Effects Key Makeup Artist"}], "id": 18660}}