{"cached_at": "2025-03-31T22:10:21.008571", "value": {"cast": [{"adult": false, "gender": 1, "id": 194670, "known_for_department": "Acting", "name": "Tahnee Welch", "original_name": "Tahnee Welch", "popularity": 0.4371, "profile_path": "/htfVpV7K9NEYIRMAebBVzocOd9I.jpg", "character": "Giulia de Blasco", "credit_id": "610be9acee43e80027cf97a0", "order": 0}, {"adult": false, "gender": 2, "id": 21181, "known_for_department": "Acting", "name": "Fabio Testi", "original_name": "Fabio Testi", "popularity": 0.3336, "profile_path": "/a91IAsHaUr9vinlKBjebXVp8c4x.jpg", "character": "Ermes Corsini", "credit_id": "610be9c1ee43e8005e43c830", "order": 1}, {"adult": false, "gender": 1, "id": 29918, "known_for_department": "Acting", "name": "Dalila Di Lazzaro", "original_name": "Dalila Di Lazzaro", "popularity": 0.2939, "profile_path": "/3ile65ri3ncUzH02TiAcxMvJ3Fa.jpg", "character": "Marta Montini", "credit_id": "610be9d3323eba002fbbf2c0", "order": 2}, {"adult": false, "gender": 2, "id": 32377, "known_for_department": "Acting", "name": "Enrico Maria Salerno", "original_name": "Enrico Maria Salerno", "popularity": 0.2775, "profile_path": "/hiiJVxSyTVKq1OK4gVqGy0xu542.jpg", "character": "Ubaldo Milkovich", "credit_id": "610be9e7b234b9005eceed59", "order": 3}, {"adult": false, "gender": 2, "id": 147591, "known_for_department": "Acting", "name": "St\u00e9phane Ferrara", "original_name": "St\u00e9phane Ferrara", "popularity": 0.1772, "profile_path": "/tl56De7p6sgIuiY5QocJu5S3G7b.jpg", "character": "Leo Rovelli", "credit_id": "610be9fa4cbe12002c5c6639", "order": 4}, {"adult": false, "gender": 2, "id": 85648, "known_for_department": "Acting", "name": "Eros Pagni", "original_name": "Eros Pagni", "popularity": 0.1206, "profile_path": "/scIKz8Ordl5ONCO0firEXOJCx0e.jpg", "character": "Vittoiro de Blasco", "credit_id": "610bea0bee43e8007f3eed1d", "order": 5}, {"adult": false, "gender": 1, "id": 10476, "known_for_department": "Acting", "name": "Corinne Cl\u00e9ry", "original_name": "Corinne Cl\u00e9ry", "popularity": 0.1837, "profile_path": "/xFo2LlhaLkYJQVxhddE7eovrgoS.jpg", "character": "Elena Dionisi", "credit_id": "610bea1ae61e6d007550e36a", "order": 6}, {"adult": false, "gender": 2, "id": 19162, "known_for_department": "Acting", "name": "Jean-Pierre Cassel", "original_name": "Jean-Pierre Cassel", "popularity": 0.4858, "profile_path": "/iCZ9CFw55lwdERGuIEFrkpOdaBi.jpg", "character": "", "credit_id": "610bea2a323eba007362bd28", "order": 7}, {"adult": false, "gender": 2, "id": 128926, "known_for_department": "Acting", "name": "Bekim Fehmiu", "original_name": "Bekim Fehmiu", "popularity": 0.0713, "profile_path": "/qrHE9YYHAXoxaz5inf2YvL5DbXx.jpg", "character": "Armando Zani #2", "credit_id": "610bea3b7719d7004576bb5c", "order": 8}, {"adult": false, "gender": 1, "id": 224299, "known_for_department": "Acting", "name": "Marina Suma", "original_name": "Marina Suma", "popularity": 0.1592, "profile_path": "/4MGjy8u5j5nhlYJwGNO5BD6kc32.jpg", "character": "Zaira", "credit_id": "610bea4db234b90074e612e1", "order": 9}, {"adult": false, "gender": 1, "id": 35956, "known_for_department": "Acting", "name": "Laura Antonelli", "original_name": "Laura Antonelli", "popularity": 0.514, "profile_path": "/6pwHBvKtro1jcJmXdotKB3ShUQZ.jpg", "character": "Carmen Milkovich", "credit_id": "610bea5f9f5dfb007ee7b2bb", "order": 10}], "crew": [], "id": 130564}}