{"cached_at": "2025-04-01T18:52:14.066283", "value": {"cast": [{"adult": false, "gender": 1, "id": 1245779, "known_for_department": "Acting", "name": "Sheron Menezes", "original_name": "Sheron Menezzes", "popularity": 0.1821, "profile_path": "/gsimKuyssbTCn1a7QUln9zyjyNK.jpg", "character": "Solange (Sol)", "credit_id": "631e529c3a4a12007dcb8a24", "order": 0}, {"adult": false, "gender": 2, "id": 2036877, "known_for_department": "Acting", "name": "Samuel de Assis", "original_name": "Samuel de Assis", "popularity": 0.1634, "profile_path": "/sNOPY6VBL1P77wMA7e4qda3M1SI.jpg", "character": "Benjamim (Ben)", "credit_id": "631e54650102c900818d96be", "order": 1}, {"adult": false, "gender": 2, "id": 1337505, "known_for_department": "Acting", "name": "Jos\u00e9 Loreto", "original_name": "Jos\u00e9 Loreto", "popularity": 0.1255, "profile_path": "/nnK0FZvHiEX8ehg6pwVQjhjoKoS.jpg", "character": "Lui Lorenzo", "credit_id": "631e52a69c24fc0091e28d2f", "order": 2}, {"adult": false, "gender": 1, "id": 583627, "known_for_department": "Acting", "name": "Carolina Dieckmann", "original_name": "Carolina Dieckmann", "popularity": 0.3705, "profile_path": "/rBC86RYNPgMP4633rXEu5ejk3Rq.jpg", "character": "Lumiar", "credit_id": "631e52db0102c9007e3fefdb", "order": 3}, {"adult": false, "gender": 2, "id": 1471569, "known_for_department": "Acting", "name": "Em\u00edlio Dantas", "original_name": "Em\u00edlio Dantas", "popularity": 0.1224, "profile_path": "/vUK371XD6QmvCjhYCoLJEFTsfaK.jpg", "character": "Theo", "credit_id": "63255b46226c56007cdaa428", "order": 4}, {"adult": false, "gender": 1, "id": 3440986, "known_for_department": "Acting", "name": "Bella Campos", "original_name": "Bella Campos", "popularity": 0.1995, "profile_path": "/34B2C9IPprXNA69QFemK2TimWsN.jpg", "character": "Jenifer Daiane", "credit_id": "634f41bd158c850098be534f", "order": 5}, {"adult": false, "gender": 1, "id": 583635, "known_for_department": "Acting", "name": "Renata Sorrah", "original_name": "Renata Sorrah", "popularity": 0.3631, "profile_path": "/biibTDAu7sX2J3a8p12s5kUWjXd.jpg", "character": "Wilma", "credit_id": "631e52adc4f552007f61bf80", "order": 6}, {"adult": false, "gender": 1, "id": 568400, "known_for_department": "Acting", "name": "Regiane Alves", "original_name": "Regiane Alves", "popularity": 0.2304, "profile_path": "/8ACb8FEDKBmGzU6lgMTOEY9rZ90.jpg", "character": "Clara", "credit_id": "631e532e1ac292007aa7d57e", "order": 7}, {"adult": false, "gender": 1, "id": 3528094, "known_for_department": "Acting", "name": "Clara Moneke", "original_name": "Clara Moneke", "popularity": 0.0809, "profile_path": "/2XIFFc2ATdOMV2ckXLwI8W8I1Kz.jpg", "character": "Kate Cristina (Katel\u00edcia)", "credit_id": "638aa8837d5db5007f39c6e9", "order": 8}, {"adult": false, "gender": 2, "id": 1434226, "known_for_department": "Acting", "name": "Che Moais", "original_name": "Che Moais", "popularity": 0.0143, "profile_path": "/8zHiZtzUtRkMzhJOJOTHMhWZxdQ.jpg", "character": "Carl\u00e3o", "credit_id": "634f42b7e86017008a457069", "order": 9}, {"adult": false, "gender": 2, "id": 1392536, "known_for_department": "Acting", "name": "Jean Paulo Campos", "original_name": "Jean Paulo Campos", "popularity": 0.1632, "profile_path": "/4oKI3Xz4qDnc9h1GuNhr2uhB4GK.jpg", "character": "Yuri dos Santos", "credit_id": "631e52ecbd3209007ad0ec90", "order": 10}, {"adult": false, "gender": 1, "id": 1475116, "known_for_department": "Acting", "name": "Mel Maia", "original_name": "Mel Maia", "popularity": 0.1133, "profile_path": "/u0HAGCLTupIHdf2KDIrZVUhpfAJ.jpg", "character": "Guiga", "credit_id": "631e52f4d8f44e007d5cb07a", "order": 11}, {"adult": false, "gender": 1, "id": 3486830, "known_for_department": "Acting", "name": "Let\u00edcia Salles", "original_name": "Let\u00edcia Salles", "popularity": 0.085, "profile_path": "/dufvsvunJaAhD4pjI6IjcnyQH7d.jpg", "character": "\u00c9rika", "credit_id": "631e533eb234b9008fc115c9", "order": 12}, {"adult": false, "gender": 1, "id": 1095865, "known_for_department": "Acting", "name": "Claudia Ohana", "original_name": "Claudia Ohana", "popularity": 0.3019, "profile_path": "/lValkSNv8o1jtDKwhhSvMovzEj9.jpg", "character": "Dora", "credit_id": "631e53dba33612007a458a73", "order": 13}, {"adult": false, "gender": 2, "id": 144804, "known_for_department": "Acting", "name": "Z\u00e9carlos Machado", "original_name": "Z\u00e9 Carlos Machado", "popularity": 0.1594, "profile_path": "/duYHbvdMYMl8FPrdyj8TSRC5VQE.jpg", "character": "F\u00e1bio", "credit_id": "67742107fbe3722a986192aa", "order": 14}, {"adult": false, "gender": 2, "id": 1324366, "known_for_department": "Acting", "name": "Lu\u00eds Lobianco", "original_name": "Lu\u00eds Lobianco", "popularity": 0.0645, "profile_path": "/dYdkAE73qUDOjMBid3y4CBiHWJt.jpg", "character": "Vitinho", "credit_id": "634f40b456b9f7007b119f1a", "order": 15}, {"adult": false, "gender": 0, "id": 3746993, "known_for_department": "Acting", "name": "Manu Estev\u00e3o", "original_name": "Manu Estev\u00e3o", "popularity": 0.0143, "profile_path": "/6tyxi9RPveCXYfkkeHtACUskn8p.jpg", "character": "Duda", "credit_id": "634f42e8e86017007f741be4", "order": 16}, {"adult": false, "gender": 1, "id": 1200930, "known_for_department": "Acting", "name": "Elisa Lucinda", "original_name": "Elisa Lucinda", "popularity": 0.1393, "profile_path": "/x1iCvQREawt35bLKLXFXTuNsTOo.jpg", "character": "Dona Marlene", "credit_id": "634f42f44ca676007fe23b42", "order": 17}, {"adult": false, "gender": 2, "id": 3543035, "known_for_department": "Acting", "name": "Guthierry Sotero", "original_name": "Guthierry Sotero", "popularity": 0.0214, "profile_path": "/x2MwLTzuSDC2lnXclX9Z2QaMtwX.jpg", "character": "Vini", "credit_id": "640b13e9caaca200fdb93d15", "order": 18}, {"adult": false, "gender": 2, "id": 592380, "known_for_department": "Acting", "name": "Caio Manhente", "original_name": "Caio Manhente", "popularity": 0.1649, "profile_path": "/7qs1dZZLQAvUlw7L506U3MwbNX5.jpg", "character": "Rafael", "credit_id": "638507f52e06970245e7419a", "order": 19}, {"adult": false, "gender": 1, "id": 2483673, "known_for_department": "Acting", "name": "Carla Cristina Cardoso", "original_name": "Carla Cristina Cardoso", "popularity": 0.0777, "profile_path": "/4jt6JuERPRTSqFSR6TQbS1UbNpQ.jpg", "character": "Bruna", "credit_id": "638aa8191283e9007c73e28b", "order": 20}, {"adult": false, "gender": 0, "id": 2507560, "known_for_department": "Acting", "name": "MC Cabelinho", "original_name": "MC Cabelinho", "popularity": 0.0558, "profile_path": "/byy8YwrFhCkqzkwWxvVq0yw2tDz.jpg", "character": "Hugo", "credit_id": "638aa8968a84d2009651185f", "order": 21}, {"adult": false, "gender": 0, "id": 2057288, "known_for_department": "Acting", "name": "Gabriel Contente", "original_name": "Gabriel Contente", "popularity": 0.0338, "profile_path": "/eubEMKixjoZ53LGzisMNBTg5KSl.jpg", "character": "Ot\u00e1vio Villar (Tat\u00e1)", "credit_id": "638d52611283e90083234a76", "order": 22}, {"adult": false, "gender": 2, "id": 8599, "known_for_department": "Acting", "name": "Jonathan Haagensen", "original_name": "Jonathan Haagensen", "popularity": 0.1853, "profile_path": "/cha3GxI1MfbCjc973iUNKUvopQF.jpg", "character": "Orfeu", "credit_id": "6395ed03a1a9ba00942fbcd6", "order": 23}, {"adult": false, "gender": 1, "id": 1963798, "known_for_department": "Acting", "name": "Nath\u00e1lia Costa", "original_name": "Nath\u00e1lia Costa", "popularity": 0.0922, "profile_path": "/x0sNL7QjUWv456RNTtCJbw7sdC.jpg", "character": "Meire", "credit_id": "63ef927b35818f0081d2f759", "order": 24}, {"adult": false, "gender": 2, "id": 1278433, "known_for_department": "Acting", "name": "Marcos Veras", "original_name": "Marcos Veras", "popularity": 0.0717, "profile_path": "/rtereNyXXCWjELvZ1rRIS1x1JjB.jpg", "character": "Simas", "credit_id": "63ef92b845765d0089dbf304", "order": 25}, {"adult": false, "gender": 0, "id": 3925211, "known_for_department": "Acting", "name": "Orlando Caldeira", "original_name": "Orlando Caldeira", "popularity": 0.0214, "profile_path": "/2H0ds9ntU2mBpsCd6D0EgXmg1Eu.jpg", "character": "Anthony Ver\u00e3o", "credit_id": "63ef92de0f0da5007be1913d", "order": 26}, {"adult": false, "gender": 1, "id": 2214746, "known_for_department": "Acting", "name": "Priscila Steinman", "original_name": "Priscila Steinman", "popularity": 0.0867, "profile_path": "/sa6Q3rCMqUaPeKdtMBQqxBOJnM.jpg", "character": "Helena", "credit_id": "63ef933bcddbbc00b2ad7e3c", "order": 27}, {"adult": false, "gender": 2, "id": 1558769, "known_for_department": "Acting", "name": "Bruno Padilha", "original_name": "Bruno Padilha", "popularity": 0.0994, "profile_path": "/2xosYVYjvgegWs7jUY3MBx97XT6.jpg", "character": "Em\u00edlio", "credit_id": "63ef936a35818f0085ea0069", "order": 28}, {"adult": false, "gender": 0, "id": 3925216, "known_for_department": "Acting", "name": "J\u00ea Soares", "original_name": "J\u00ea Soares", "popularity": 0.0143, "profile_path": "/kcOJkExDEhlVfVaLoyf6g5E8BjM.jpg", "character": "Sol Jovem", "credit_id": "63ef93d7cddbbc00d5e4fcff", "order": 29}, {"adult": false, "gender": 2, "id": 2139471, "known_for_department": "Acting", "name": "Isacque Lopes", "original_name": "Isacque Lopes", "popularity": 0.0311, "profile_path": "/rwLtULvKkO104UNqz8X9s6dNC3t.jpg", "character": "Ben (Jovem)", "credit_id": "63ef93ec35818f00db3d79c6", "order": 30}, {"adult": false, "gender": 1, "id": 2221687, "known_for_department": "Acting", "name": "Hanna Romanazzi", "original_name": "Hanna Romanazzi", "popularity": 0.0621, "profile_path": "/gY4xht2wBfOuLtFv6BlcGBk8ZWT.jpg", "character": "Lumiar (Jovem)", "credit_id": "63ef93ffcddbbc0096981aa2", "order": 31}, {"adult": false, "gender": 0, "id": 3376946, "known_for_department": "Acting", "name": "Mateus Honori", "original_name": "Mateus Honori", "popularity": 0.0, "profile_path": "/dMsczJ5kmeGS6KbzcWUj67FnRWm.jpg", "character": "Carl\u00e3o (Jovem)", "credit_id": "63ef9413cddbbc008c20ce77", "order": 32}, {"adult": false, "gender": 0, "id": 3925218, "known_for_department": "Acting", "name": "Matheus Polis", "original_name": "Matheus Polis", "popularity": 0.0, "profile_path": "/86KagxDrlBj5ozRA78Adg5strKK.jpg", "character": "Th\u00e9o (Jovem)", "credit_id": "63ef942545765d00b9a40cdb", "order": 33}, {"adult": false, "gender": 0, "id": 3394552, "known_for_department": "Acting", "name": "Rhavine Chrispim", "original_name": "Rhavine Chrispim", "popularity": 0.0429, "profile_path": "/yPbLZC7PfNJnLd7ntySaQfI6e1z.jpg", "character": "Marlene (Jovem)", "credit_id": "63ef944fea84c70096efa30b", "order": 34}, {"adult": false, "gender": 1, "id": 3949208, "known_for_department": "Acting", "name": "Flora Camolese", "original_name": "Flora Camolese", "popularity": 0.0143, "profile_path": "/cAP6h7JJdn8ngJ2iHJ7NYJ0k5s1.jpg", "character": "Bia", "credit_id": "6403f95fe61e6d008e3fd898", "order": 35}, {"adult": false, "gender": 0, "id": 3876902, "known_for_department": "Acting", "name": "Tati Villela", "original_name": "Tati Villela", "popularity": 0.0143, "profile_path": "/d4Q0YBeO2RJWZ3NUhtap00YAOYQ.jpg", "character": "Naira", "credit_id": "6403f9ab67dcc9008819f5c0", "order": 36}, {"adult": false, "gender": 2, "id": 3734853, "known_for_department": "Acting", "name": "Henrique Barreira", "original_name": "Henrique Barreira", "popularity": 0.0289, "profile_path": "/eLRdooWTNRXs5UWJ77ayuyLkFUy.jpg", "character": "Fred", "credit_id": "647b5fb10e29a20133c397f9", "order": 37}], "crew": [{"adult": false, "gender": 1, "id": 558071, "known_for_department": "Creator", "name": "Rosane Svartman", "original_name": "Rosane Svartman", "popularity": 0.1587, "profile_path": "/fDn3KSuu6QJi2m4GWdy0UiM39sW.jpg", "credit_id": "63192fc246e75f00888b4332", "department": "Writing", "job": "Writer"}, {"adult": false, "gender": 0, "id": 3692433, "known_for_department": "Writing", "name": "Pedro Alvarenga", "original_name": "Pedro Alvarenga", "popularity": 0.0379, "profile_path": null, "credit_id": "63192ff16f43ec0099ce8fbf", "department": "Writing", "job": "Writer"}, {"adult": false, "gender": 0, "id": 2481675, "known_for_department": "Acting", "name": "Paula Teixeira", "original_name": "Paula Teixeira", "popularity": 0.0143, "profile_path": null, "credit_id": "631930cc8ddc34007fa1e065", "department": "Production", "job": "Researcher"}, {"adult": false, "gender": 0, "id": 1435949, "known_for_department": "Crew", "name": "Renata Corr\u00eaa", "original_name": "Renata Corr\u00eaa", "popularity": 0.0143, "profile_path": null, "credit_id": "6319304e40d0fe0099bbcb71", "department": "Writing", "job": "Writer"}, {"adult": false, "gender": 2, "id": 2054144, "known_for_department": "Directing", "name": "Paulo Silvestrini", "original_name": "Paulo Silvestrini", "popularity": 1.0409, "profile_path": "/Al9euS2l4VePYkPrG2SKSG2sEt8.jpg", "credit_id": "631930dfcaef2d007e727ad5", "department": "Directing", "job": "Director"}, {"adult": false, "gender": 2, "id": 2126964, "known_for_department": "Writing", "name": "M\u00e1rio Viana", "original_name": "M\u00e1rio Viana", "popularity": 0.0256, "profile_path": null, "credit_id": "63192fd41d1bf4007ea0b404", "department": "Writing", "job": "Writer"}, {"adult": false, "gender": 1, "id": 2002288, "known_for_department": "Acting", "name": "Sabrina Rosa", "original_name": "Sabrina Rosa", "popularity": 0.1921, "profile_path": "/t8dXoJ5nLR18Kb5wZcjfXyPiwR2.jpg", "credit_id": "6374155aeb093200cd35953a", "department": "Writing", "job": "Writer"}, {"adult": false, "gender": 1, "id": 3787818, "known_for_department": "Writing", "name": "Renata Sofia", "original_name": "Renata Sofia", "popularity": 0.0557, "profile_path": null, "credit_id": "6374153468ff700084774d3e", "department": "Writing", "job": "Writer"}, {"adult": false, "gender": 2, "id": 1268525, "known_for_department": "Acting", "name": "Fabr\u00edcio Santiago", "original_name": "Fabr\u00edcio Santiago", "popularity": 0.0579, "profile_path": "/qB45raxIFK0X3bzShSiDuYodcNO.jpg", "credit_id": "63d01273a14e10009d432308", "department": "Writing", "job": "Writer"}, {"adult": false, "gender": 2, "id": 1943998, "known_for_department": "Directing", "name": "Cristiano Marques", "original_name": "Cristiano Marques", "popularity": 0.0286, "profile_path": "/25eV2kdPHrVR1XnTYkBpSjJdE4O.jpg", "credit_id": "63d012b291745b0081077730", "department": "Directing", "job": "Director"}, {"adult": false, "gender": 2, "id": 3851098, "known_for_department": "Directing", "name": "Matheus Senra", "original_name": "Matheus Senra", "popularity": 0.0, "profile_path": null, "credit_id": "67dcfcfdc70acdd9df697430", "department": "Directing", "job": "Director"}, {"adult": false, "gender": 1, "id": 1903228, "known_for_department": "Directing", "name": "Isabella Teixeira", "original_name": "Isabella Teixeira", "popularity": 0.0214, "profile_path": "/jIW5qxY01w0wAFiUKwzFcGtCvEB.jpg", "credit_id": "67dcfd35c28404e629f53cf0", "department": "Directing", "job": "Director"}, {"adult": false, "gender": 1, "id": 2750552, "known_for_department": "Directing", "name": "Juh Almeida", "original_name": "Juh Almeida", "popularity": 0.0071, "profile_path": null, "credit_id": "67dcfd540416875adc697745", "department": "Directing", "job": "Director"}, {"adult": false, "gender": 0, "id": 3849518, "known_for_department": "Directing", "name": "Augusto Lana", "original_name": "Augusto Lana", "popularity": 0.0168, "profile_path": null, "credit_id": "67dcfd720416875adc697750", "department": "Directing", "job": "Director"}], "id": 209117}}