{"cached_at": "2025-03-31T22:04:54.574935", "value": {"cast": [{"adult": false, "gender": 0, "id": 1216059, "known_for_department": "Acting", "name": "Jamie Redknapp", "original_name": "Jamie Redknapp", "popularity": 0.0495, "profile_path": "/f2a36d7QVCNWShrVsbsILtAhV0k.jpg", "character": "", "credit_id": "664c95c9403b3a6a55f2dd88", "order": 0}, {"adult": false, "gender": 2, "id": 2185015, "known_for_department": "Acting", "name": "Mo Gilligan", "original_name": "Mo Gilligan", "popularity": 0.2719, "profile_path": "/i6heWKdRr6QJYO9VZ3ag2kFsE9H.jpg", "character": "", "credit_id": "664c96342c95d9fcdb259b3d", "order": 1}, {"adult": false, "gender": 1, "id": 3639580, "known_for_department": "Acting", "name": "Jill Scott", "original_name": "Jill Scott", "popularity": 0.2212, "profile_path": "/lXqzZfwLeyu9okjrntZsJv6hvK4.jpg", "character": "", "credit_id": "664c963e2319669d9c92ef86", "order": 2}, {"adult": false, "gender": 2, "id": 1304658, "known_for_department": "Acting", "name": "Romesh Ranganathan", "original_name": "Romesh Ranganathan", "popularity": 0.3763, "profile_path": "/kZ4g2kvgx8MHKLEQ7DAQ07ta2Lz.jpg", "character": "", "credit_id": "66601e9eb60dbe6ae4007ecc", "order": 3}], "crew": [], "id": 255005}}