{"cached_at": "2025-04-02T00:19:08.329047", "value": {"id": 299471, "name": "Season 1", "season_number": 1, "episode_count": null, "air_date": "2022-09-27", "episodes": [{"id": 3816606, "name": "Can't Knock the Hustle", "episode_number": 1, "air_date": "2022-09-27"}, {"id": 3817153, "name": "Family Feud", "episode_number": 2, "air_date": "2022-09-27"}, {"id": 3976464, "name": "99 Problems", "episode_number": 3, "air_date": "2022-10-04"}, {"id": 3976465, "name": "Guilty Until Proven Innocent", "episode_number": 4, "air_date": "2022-10-11"}, {"id": 3976466, "name": "So Ambitious", "episode_number": 5, "air_date": "2022-10-18"}, {"id": 3976467, "name": "Renegade", "episode_number": 6, "air_date": "2022-10-25"}, {"id": 3976468, "name": "N**** What, N**** Who", "episode_number": 7, "air_date": "2022-11-01"}, {"id": 3976469, "name": "Song Cry", "episode_number": 8, "air_date": "2022-11-08"}, {"id": 3976470, "name": "Already Home", "episode_number": 9, "air_date": "2022-11-15"}]}}