{"cached_at": "2025-03-31T22:02:13.680088", "value": {"id": 139474, "name": "Run the Burbs", "original_name": "Run the Burbs", "overview": "Follow the Phams, a young, bold Vietnamese-South Asian-Canadian family taking a different approach to living life to the fullest, while changing the way we think about contemporary family values and life in the burbs.", "first_air_date": "2022-01-05", "genre_ids": [], "popularity": 7.4834, "vote_average": 6.1, "vote_count": 14, "genres": [{"id": 35, "name": "Comedy"}, {"id": 10751, "name": "Family"}], "networks": [{"id": 23, "name": "CBC Television"}], "status": "Canceled", "type": "Scripted", "number_of_seasons": 3, "number_of_episodes": 38, "in_production": false, "languages": ["en"], "last_air_date": "2024-04-02"}}