{"cached_at": "2025-03-30T17:58:49.979971", "value": {"cast": [{"adult": false, "gender": 1, "id": 119143, "known_for_department": "Acting", "name": "Kana Hanazawa", "original_name": "\u82b1\u6fa4\u9999\u83dc", "popularity": 2.0697, "profile_path": "/rYbVloKRRK3gRTVAf3Mbj9xak4Z.jpg", "character": "Baileu Ton (voice)", "credit_id": "5fab01f9a6d9310041a41fb3", "order": 0}, {"adult": false, "gender": 2, "id": 9705, "known_for_department": "Acting", "name": "Takahiro Sakurai", "original_name": "\u6afb\u4e95\u5b5d\u5b8f", "popularity": 2.8909, "profile_path": "/8s8owcKmpRAuhzEGjSdRpztthUg.jpg", "character": "Vlad Garfunkel (voice)", "credit_id": "5fab021a72c13e0041778bfd", "order": 1}, {"adult": false, "gender": 2, "id": 1245094, "known_for_department": "Acting", "name": "Nobuhiko Okamoto", "original_name": "\u5ca1\u672c\u4fe1\u5f66", "popularity": 1.3301, "profile_path": "/7s1K2yQVF5iIWILaOfG7QrMZkXA.jpg", "character": "Luke Bowen (voice)", "credit_id": "5fab023b85c0a2003fdb24e3", "order": 2}, {"adult": false, "gender": 2, "id": 144655, "known_for_department": "Acting", "name": "Tomokazu Sugita", "original_name": "\u6749\u7530\u667a\u548c", "popularity": 1.5376, "profile_path": "/cv5zuPZySNsHXu24pjKLYCRzJ2J.jpg", "character": "Touryuu (voice)", "credit_id": "5fab02662a09bc00418eeb5e", "order": 3}, {"adult": false, "gender": 2, "id": 1325962, "known_for_department": "Acting", "name": "Daiki Yamashita", "original_name": "\u5c71\u4e0b\u5927\u8f1d", "popularity": 0.807, "profile_path": "/rQNdJdZewk7VGP16ZNbpfJ9ZeMd.jpg", "character": "Wayne King (voice)", "credit_id": "5fab0293875d1a003f0b5add", "order": 4}, {"adult": false, "gender": 2, "id": 237076, "known_for_department": "Acting", "name": "Rikiya Koyama", "original_name": "\u5c0f\u5c71\u529b\u4e5f", "popularity": 1.1638, "profile_path": "/hsZm87BORLpzhaycBaWOD5xpjVC.jpg", "character": "Van Helsing (voice)", "credit_id": "5fab02c78de0ae0042b992b6", "order": 5}, {"adult": false, "gender": 2, "id": 9721, "known_for_department": "Acting", "name": "Junichi Suwabe", "original_name": "\u8acf\u8a2a\u90e8\u9806\u4e00", "popularity": 1.0912, "profile_path": "/4S7c3n3r07A83HvkLrnWZGVhiHg.jpg", "character": "Haysin (voice)", "credit_id": "5fab02ec63d7130040982134", "order": 6}, {"adult": false, "gender": 2, "id": 1206317, "known_for_department": "Acting", "name": "Yuki Ono", "original_name": "\u5c0f\u91ce\u53cb\u6a39", "popularity": 0.9437, "profile_path": "/oEx13CbNLsHzURdYafkFJYXDjfm.jpg", "character": "Chris (voice)", "credit_id": "5fab030a2f3b17003ff1bf7f", "order": 7}, {"adult": false, "gender": 1, "id": 1835721, "known_for_department": "Acting", "name": "Manaka Iwami", "original_name": "\u77f3\u898b\u821e\u83dc\u9999", "popularity": 0.7554, "profile_path": "/leKMaCBswXG8u4mfQNQ7J3y6Xow.jpg", "character": "Mu Shinyao (voice)", "credit_id": "5fab0327bf31f20041e164ba", "order": 8}, {"adult": false, "gender": 1, "id": 202806, "known_for_department": "Acting", "name": "Yui Horie", "original_name": "\u5800\u6c5f\u7531\u8863", "popularity": 1.4744, "profile_path": "/73yQlMWaiOMrhvPCNyOCbbCkILZ.jpg", "character": "Sha Rijan (voice)", "credit_id": "5fab038f1d019100407c7e37", "order": 9}, {"adult": false, "gender": 2, "id": 9716, "known_for_department": "Acting", "name": "Kenji Nomura", "original_name": "\u4e43\u6751\u5065\u6b21", "popularity": 0.3508, "profile_path": "/rmTziYxlPje4PiKhPgqMEHu9Axd.jpg", "character": "George L. Gregory (voice)", "credit_id": "6081475201b1ca00586aee68", "order": 10}], "crew": [{"adult": false, "gender": 1, "id": 2282935, "known_for_department": "Editing", "name": "Tomomi Umetsu", "original_name": "\u6885\u6d25\u670b\u7f8e", "popularity": 0.1944, "profile_path": null, "credit_id": "60a7f60bbbd0b000424dbf9d", "department": "Editing", "job": "Editor"}, {"adult": false, "gender": 0, "id": 1582053, "known_for_department": "Production", "name": "Nao Hirasawa", "original_name": "\u5e73\u6fa4\u76f4", "popularity": 0.0214, "profile_path": null, "credit_id": "67e69ed8027e737406004edf", "department": "Production", "job": "Producer"}], "id": 80561}}