{"cached_at": "2025-03-31T22:10:48.039803", "value": {"cast": [{"adult": false, "gender": 1, "id": 549566, "known_for_department": "Acting", "name": "Eiko Yamada", "original_name": "\u5c71\u7530\u6804\u5b50", "popularity": 1.3204, "profile_path": "/uIESaPrL2AxOaYyfmh6krMVe813.jpg", "character": "Anne Shirley (voice)", "credit_id": "642e988654a8ac0b5758c688", "order": 0}, {"adult": false, "gender": 1, "id": 552640, "known_for_department": "Acting", "name": "Fumie Kitahara", "original_name": "\u5317\u539f\u6587\u679d", "popularity": 0.2593, "profile_path": "/dE9HcKFIIJhO5c01GosNW8iA02r.jpg", "character": "Marilla Cuthbert (voice)", "credit_id": "52584c5f760ee346610056fd", "order": 1}, {"adult": false, "gender": 2, "id": 553057, "known_for_department": "Acting", "name": "Ry\u016bji Saikachi", "original_name": "\u69d0\u67f3\u4e8c", "popularity": 0.26, "profile_path": "/fGCuIdYNTiP7U6jqfPEUaPn8FXi.jpg", "character": "Matthew Cuthbert (voice)", "credit_id": "52584c5d760ee346610056ea", "order": 2}, {"adult": false, "gender": 1, "id": 20663, "known_for_department": "Acting", "name": "Gara Takashima", "original_name": "\u9ad8\u5cf6\u96c5\u7f85", "popularity": 0.389, "profile_path": "/5L0kzTVITmOQdQ94NhicKM8ecCX.jpg", "character": "Diana Barry (voice)", "credit_id": "52584c5f760ee3466100570d", "order": 3}, {"adult": false, "gender": 2, "id": 554418, "known_for_department": "Acting", "name": "Michio Hazama", "original_name": "\u7fbd\u4f50\u9593\u9053\u592b", "popularity": 0.2029, "profile_path": "/vjHAu5T8n04uhJ9CSaEAkXwEABQ.jpg", "character": "Narrator (voice)", "credit_id": "642975338de0ae00978d6c2a", "order": 4}, {"adult": false, "gender": 2, "id": 89968, "known_for_department": "Acting", "name": "Kazuhiko Inoue", "original_name": "\u4e95\u4e0a\u548c\u5f66", "popularity": 1.1817, "profile_path": "/3BpYtYRiLAmTNbCm2LXlXnkMRit.jpg", "character": "Gilbert Blythe (voice)", "credit_id": "52584c5d760ee346610056da", "order": 5}, {"adult": false, "gender": 1, "id": 549563, "known_for_department": "Acting", "name": "Sanae Takagi", "original_name": "\u9ad8\u6728\u65e9\u82d7", "popularity": 0.2018, "profile_path": "/64adMkVDrzFQUjS1mxO2pdDEWvG.jpg", "character": "Jane Andrews (voice)", "credit_id": "52584c5d760ee346610056ba", "order": 6}, {"adult": false, "gender": 1, "id": 1680, "known_for_department": "Acting", "name": "Mami Koyama", "original_name": "\u5c0f\u5c71\u8309\u7f8e", "popularity": 0.7372, "profile_path": "/4KjDxYsa7mMh8gbqSKCV2DixDAx.jpg", "character": "Ruby Gillis / Minnie May Barry (voice)", "credit_id": "642973ee8de0ae00b654fc7d", "order": 7}, {"adult": false, "gender": 1, "id": 1242448, "known_for_department": "Acting", "name": "Hiroko Suzuki", "original_name": "\u9234\u6728\u5f18\u5b50", "popularity": 0.2212, "profile_path": "/a0wCgDPI5hcR3AcxxFbJghDic0U.jpg", "character": "Muriel Stacey (voice)", "credit_id": "52584c5f760ee3466100577d", "order": 8}, {"adult": false, "gender": 1, "id": 1055172, "known_for_department": "Acting", "name": "Junko Hori", "original_name": "\u5800\u7d62\u5b50", "popularity": 0.2784, "profile_path": "/nMacN4CiR6BvjYsbk2rguyeyCye.jpg", "character": "Josie Pye (voice)", "credit_id": "62a5c6267e12f02ff65e63ed", "order": 9}, {"adult": false, "gender": 1, "id": 1244634, "known_for_department": "Acting", "name": "Kazuyo Aoki", "original_name": "\u9752\u6728\u548c\u4ee3", "popularity": 0.2684, "profile_path": "/rNPELlTHGOn36Ip3hToWdTGeufi.jpg", "character": "Charlie Sloane (voice)", "credit_id": "52584c60760ee346610057cd", "order": 10}, {"adult": false, "gender": 2, "id": 235337, "known_for_department": "Acting", "name": "Yoku Shioya", "original_name": "\u5869\u5c4b\u7ffc", "popularity": 0.3176, "profile_path": "/zJCaOJWub2g8ZlXuH8vE9yaBVy1.jpg", "character": "Moody Spurgeon (voice)", "credit_id": "52584c5f760ee3466100573d", "order": 11}, {"adult": false, "gender": 1, "id": 551973, "known_for_department": "Acting", "name": "Reiko Mutoh", "original_name": "\u6b66\u85e4\u793c\u5b50", "popularity": 0.2311, "profile_path": "/ekSCGLyBJjvzsurtFdSQ7Q2Fp90.jpg", "character": "Mrs. Elizabeth Barry (voice)", "credit_id": "52584c5f760ee3466100572d", "order": 12}, {"adult": false, "gender": 1, "id": 1066413, "known_for_department": "Acting", "name": "Miyoko As\u00f4", "original_name": "\u9ebb\u751f\u7f8e\u4ee3\u5b50", "popularity": 0.2213, "profile_path": "/qi47sHVnXxTWCiOlRwgvL460SJI.jpg", "character": "Rachel Lynde (voice)", "credit_id": "52584c5f760ee3466100575d", "order": 13}, {"adult": false, "gender": 0, "id": 1692740, "known_for_department": "Acting", "name": "Saiko Egawa", "original_name": "Saiko Egawa", "popularity": 0.0214, "profile_path": null, "character": "Mrs. Allan / Priscilla Grant / Prissy Andrews (voice)", "credit_id": "6429f2ae66540800f4341c82", "order": 14}, {"adult": false, "gender": 2, "id": 122653, "known_for_department": "Acting", "name": "Kazuyuki Sogabe", "original_name": "\u66fd\u6211\u90e8\u548c\u606d", "popularity": 0.363, "profile_path": "/mRKCnfm8S6NiBkf93QT9vdIpFKJ.jpg", "character": "Minister Allan (voice)", "credit_id": "52584c5f760ee3466100578d", "order": 15}, {"adult": false, "gender": 2, "id": 555346, "known_for_department": "Acting", "name": "Ritsuo Sawa", "original_name": "\u6ca2\u308a\u3064\u304a", "popularity": 0.2138, "profile_path": "/kyjtLi4KBymdTgQz1WDI1ifiaZk.jpg", "character": "Martin (voice)", "credit_id": "5af52fc20e0a26425f0022fd", "order": 16}, {"adult": false, "gender": 1, "id": 1255972, "known_for_department": "Acting", "name": "Natsuko Kawaji", "original_name": "\u5ddd\u8def\u590f\u5b50", "popularity": 0.1461, "profile_path": null, "character": "Josephine Barry (voice)", "credit_id": "6429750da3e4ba1cd8111957", "order": 17}, {"adult": false, "gender": 2, "id": 1244349, "known_for_department": "Acting", "name": "Eisuke Yoda", "original_name": "\u4f9d\u7530\u82f1\u52a9", "popularity": 0.1403, "profile_path": null, "character": "Mr. Barry (voice)", "credit_id": "52584c5f760ee346610057ad", "order": 18}, {"adult": false, "gender": 1, "id": 1129846, "known_for_department": "Acting", "name": "Michiko Hirai", "original_name": "\u5e73\u4e95\u9053\u5b50", "popularity": 0.1379, "profile_path": null, "character": "Mrs. Amelia Evans (voice)", "credit_id": "52584c5f760ee3466100571d", "order": 19}, {"adult": false, "gender": 1, "id": 1184454, "known_for_department": "Acting", "name": "Chiyoko Kawashima", "original_name": "\u5ddd\u5cf6\u5343\u4ee3\u5b50", "popularity": 1.39, "profile_path": null, "character": "Tilly Boulter (voice)", "credit_id": "52584c5f760ee3466100576d", "order": 20}, {"adult": false, "gender": 0, "id": 1244472, "known_for_department": "Acting", "name": "Kimiko Tsuruta", "original_name": "Kimiko Tsuruta", "popularity": 0.0, "profile_path": null, "character": "Sophia Sloane (voice)", "credit_id": "52584c5f760ee3466100579d", "order": 21}, {"adult": false, "gender": 2, "id": 215919, "known_for_department": "Acting", "name": "Motomu Kiyokawa", "original_name": "\u6e05\u5ddd\u5143\u5922", "popularity": 0.4821, "profile_path": "/ohqgdiyBnZjXMtwi0Z3RQxXfVhF.jpg", "character": "Teddy Philips (voice)", "credit_id": "52584c60760ee346610057dd", "order": 22}, {"adult": false, "gender": 1, "id": 621, "known_for_department": "Acting", "name": "Rihoko Yoshida", "original_name": "\u5409\u7530\u7406\u4fdd\u5b50", "popularity": 0.6312, "profile_path": "/iw81OKtwp4tII3k0IwUloHwJjBd.jpg", "character": "Flora Jane Spencer (voice)", "credit_id": "52584c60760ee346610057ed", "order": 23}], "crew": [{"adult": false, "gender": 0, "id": 1473143, "known_for_department": "Art", "name": "Masahiro Ioka", "original_name": "Masahiro Ioka", "popularity": 0.0071, "profile_path": null, "credit_id": "5af52fa10e0a2642480021ed", "department": "Art", "job": "Art Direction"}, {"adult": false, "gender": 0, "id": 1607412, "known_for_department": "Writing", "name": "Shigeki Chiba", "original_name": "Shigeki Chiba", "popularity": 0.0457, "profile_path": null, "credit_id": "5ff26e8166e4690040c16449", "department": "Writing", "job": "Writer"}, {"adult": false, "gender": 0, "id": 2922360, "known_for_department": "Writing", "name": "Seijiro Kamiyama", "original_name": "Seijiro Kamiyama", "popularity": 0.0143, "profile_path": null, "credit_id": "5ff26ef75507e900400c332c", "department": "Writing", "job": "Writer"}, {"adult": false, "gender": 2, "id": 552038, "known_for_department": "Writing", "name": "Yoshihisa Araki", "original_name": "\u8352\u6728\u82b3\u4e45", "popularity": 0.1093, "profile_path": null, "credit_id": "5ff26f291fb94f0041f7229f", "department": "Writing", "job": "Writer"}, {"adult": false, "gender": 0, "id": 1607413, "known_for_department": "Writing", "name": "Aiko Isomura", "original_name": "Aiko Isomura", "popularity": 0.0071, "profile_path": null, "credit_id": "5ff26f6446e75f0040d3c298", "department": "Writing", "job": "Writer"}, {"adult": false, "gender": 0, "id": 2922362, "known_for_department": "Writing", "name": "Takekuni Takano", "original_name": "Takekuni Takano", "popularity": 0.0, "profile_path": null, "credit_id": "5ff26f7a1d3563003e0df2a7", "department": "Writing", "job": "Writer"}, {"adult": false, "gender": 2, "id": 1198465, "known_for_department": "Sound", "name": "Kurodo Mori", "original_name": "\u6bdb\u5229\u8535\u4eba", "popularity": 0.083, "profile_path": null, "credit_id": "5ff271a9d2f5b5003e2e2396", "department": "Sound", "job": "Original Music Composer"}, {"adult": false, "gender": 2, "id": 1552569, "known_for_department": "Production", "name": "K\u014dichi Motohashi", "original_name": "\u672c\u6a4b\u6d69\u4e00", "popularity": 0.0412, "profile_path": null, "credit_id": "5ff273ca46e75f0041d36e77", "department": "Production", "job": "Producer"}, {"adult": false, "gender": 1, "id": 1277029, "known_for_department": "Writing", "name": "Lucy Maud Montgomery", "original_name": "Lucy Maud Montgomery", "popularity": 0.2084, "profile_path": "/zwGAiFCk5i7tHFeiPkSrnkAFU3p.jpg", "credit_id": "5ff27400fbe36f003ff77039", "department": "Writing", "job": "Author"}, {"adult": false, "gender": 2, "id": 608, "known_for_department": "Directing", "name": "Hayao Miyazaki", "original_name": "\u5bae\u5d0e\u99ff", "popularity": 1.9822, "profile_path": "/ouhjt9KugzhWtdEyBPipihB3ic8.jpg", "credit_id": "5ff275a77aecc60040fd9b4c", "department": "Art", "job": "Settings"}, {"adult": false, "gender": 0, "id": 2052086, "known_for_department": "Visual Effects", "name": "Michiyo Sakurai", "original_name": "Michiyo Sakurai", "popularity": 0.0143, "profile_path": null, "credit_id": "5ff2768b976e48003e691562", "department": "Art", "job": "Settings"}, {"adult": false, "gender": 2, "id": 555254, "known_for_department": "Directing", "name": "Yoshifumi Kondo", "original_name": "\u8fd1\u85e4\u559c\u6587", "popularity": 0.2791, "profile_path": "/kMGHxgP7tz4diYcGp4P4a7sHsBC.jpg", "credit_id": "5ff276ca1108a8004089d5d1", "department": "Visual Effects", "job": "Character Designer"}, {"adult": false, "gender": 0, "id": 2052146, "known_for_department": "Camera", "name": "Keishichi Kuroki", "original_name": "Keishichi Kuroki", "popularity": 0.0168, "profile_path": null, "credit_id": "5ff278a2df294500412d5fc4", "department": "Camera", "job": "Director of Photography"}, {"adult": false, "gender": 2, "id": 239826, "known_for_department": "Sound", "name": "Yasuo Uragami", "original_name": "\u6d66\u4e0a\u9756\u592b", "popularity": 0.1191, "profile_path": null, "credit_id": "5ff2790767203d003fca531f", "department": "Sound", "job": "Recording Supervision"}, {"adult": false, "gender": 1, "id": 2256310, "known_for_department": "Visual Effects", "name": "Akiko Koyama", "original_name": "Akiko Koyama", "popularity": 0.0143, "profile_path": null, "credit_id": "5ff27a1cd34eb3004151a696", "department": "Editing", "job": "Color Grading"}, {"adult": false, "gender": 1, "id": 1456795, "known_for_department": "Visual Effects", "name": "Michiyo Yasuda", "original_name": "\u4fdd\u7530\u9053\u4e16", "popularity": 0.1311, "profile_path": "/e9946d6VIHL9ftaEmlzIpu1YkOG.jpg", "credit_id": "5ff27a3f67203d003eca27c2", "department": "Editing", "job": "Color Grading"}, {"adult": false, "gender": 2, "id": 1564406, "known_for_department": "Production", "name": "Shigeo Endo", "original_name": "\u9060\u85e4\u91cd\u592b", "popularity": 0.0814, "profile_path": null, "credit_id": "5ff27a81156cc70040f1f46b", "department": "Production", "job": "Producer"}, {"adult": false, "gender": 2, "id": 1611146, "known_for_department": "Production", "name": "Junz\u014d Nakajima", "original_name": "\u4e2d\u5cf6\u9806\u4e09", "popularity": 0.0441, "profile_path": "/1WBLhwdapCBG6TLRUhKHOnZReN6.jpg", "credit_id": "5ff27aac1d3563003f0dcfdb", "department": "Production", "job": "Producer"}, {"adult": false, "gender": 2, "id": 1047602, "known_for_department": "Directing", "name": "Shigeo Koshi", "original_name": "\u8170\u7e41\u7537", "popularity": 0.0982, "profile_path": null, "credit_id": "5ff27ed5f794ad003d7240a0", "department": "Directing", "job": "Director"}, {"adult": false, "gender": 2, "id": 628, "known_for_department": "Directing", "name": "Isao Takahata", "original_name": "\u9ad8\u7551\u52f2", "popularity": 0.6153, "profile_path": "/xTkZOWe1VU4xNba1lO0T9trFLHm.jpg", "credit_id": "5ff280411d3563003e0e21f1", "department": "Directing", "job": "Series Director"}, {"adult": false, "gender": 2, "id": 628, "known_for_department": "Directing", "name": "Isao Takahata", "original_name": "\u9ad8\u7551\u52f2", "popularity": 0.6153, "profile_path": "/xTkZOWe1VU4xNba1lO0T9trFLHm.jpg", "credit_id": "5ff2808766e4690040c18edf", "department": "Writing", "job": "Series Composition"}], "id": 16047}}